Workbook

Sheet Caso Excavadora
A1: Calcule el costo horario de una excavadora hidráulica cuyo motor tiene de 200 kW, y cuenta con pluma de excavación de gran volumen y cucharon de 4 m3. El precio de una excavadora nueva es USD 250,000. La operación requiere que la excavadora produzca 150 m3/h, 3000 horas al año (no incluye mantenimiento), los 365 días del año. Considere que el valor comercial del equipo después de 5 años de uso sería USD 150,000. Asimimo la suma asegurada para un equipo se reduce 10% por cada año de antigüedad del equipo. En este caso no se tiene que pagar impuestos al fisco por la operación del equipo y el costo de almacenamiento es USD 5 por día calendario y cada vez que el equipo ingresa al taller por mantenimiento debe ser reemplazado por un equipo back up cuya producción es 125 m3/h.
A6: Item | B6: Inversión | C6: Vida óptima | D6: Horas de operación al año | E6: Consumo de combustible (gl/h) | F6: Producción (m3/h) | G6: Costo de la pérdida de producción (USD/m3) | H6: Costo del equipo back up (USD/día)
A7: Excavadora hidráulica | B7: 250000 | C7: 15000 | D7: 3000 | E7: 4.5 | F7: 150 | G7: 1 | H7: 720
A9: Item | B9: Costo promedio (USD) | C9: Frecuencia (h) | D9: Duración promedio (Día)
A10: Mantenimiento preventivo | B10: 500 | C10: 250 | D10: 1
A11: Mantenimiento correctivo | B11: 1200 | C11: 1667 | D11: 1
A12: Elementos de desgaste | B12: 1500 | C12: 500 | D12: 1
A13: Herramientas de corte | B13: 1200 | C13: 750 | D13: 0.5
A14: Neumáticos | B14: 4800 | C14: 800 | D14: 0.5

Sheet Tiempo mantenimiento
A1: Item | B1: Inversión | C1: Vida óptima (h) | D1: Horas de operación al año | E1: Consumo de combustible (gl/h) | F1: Producción (m3/h) | G1: Costo de la pérdida de producción (USD/m3) | H1: Costo del equipo back up (USD/día)
A2: Excavadora hidráulica | B2: 250000 | C2: 15000 | D2: 5000 | E2: 4.5 | F2: 80 | G2: 3.5 | H2: 720
A4: Item | B4: Costo promedio (USD) | C4: Frecuencia (h) | D4: Duración promedio (Día)
A5: Mantenimiento preventivo | B5: 500 | C5: 250 | D5: 1
A6: Mantenimiento correctivo | B6: 1200 | C6: 1667 | D6: 1
A7: Elementos de desgaste | B7: 1500 | C7: 500 | D7: 1
A8: Herramientas de corte | B8: 1200 | C8: 750 | D8: 0.5
A9: Neumáticos | B9: 4800 | C9: 800 | D9: 0.5
A12: Horas de trabajo anual | B12: 3000
A13: Dias de trabajo anual | B13: 365
A14: horas por cada día | B14: =B12/B13 -> 8.2191781
A16: Equipo nuevo | B16: # EVENTO | C16: COSTO | D16: TIEMPO
A17: Preventivo | B17: =B12/C5 -> 12 | C17: =B17*B5 -> 6000 | D17: =B17*D5 -> 12
A18: Correctivo | B18: =B12/C6 -> 1.7996401 | C18: =B18*B6 -> 2159.5681 | D18: =B18*D6 -> 1.7996401
A19: Elementos de desgaste | B19: =B12/C7 -> 6 | C19: =B19*B7 -> 9000 | D19: =B19*D7 -> 6
A20: =A8 -> Herramientas de corte | B20: =B12/C8 -> 4 | C20: =B20*B8 -> 4800 | D20: =B20*D8 -> 2
A21: Neumáticos | B21: =B12/C9 -> 3.75 | C21: =B21*B9 -> 18000 | D21: =B21*D9 -> 1.875
C22: TOTAL | D22: =SUM(D17:D21) -> 23.67464

Sheet Costos
B2: TASA DE DESCUENTO (TAMEX) | C2: 0.1589
B3: VALOR DEL EQUIPO | C3: 250000
B4: DETALLE | C4: 0 | D4: 1 | E4: 2 | F4: 3 | G4: 4 | H4: 5
B5: Inversión | C5: =-250000 -> -250000
B6: Venta de equipo anterior | C6: 0
B7: Valor residual | H7: 150000
B8: Seguros (4%) | D8: =-$C$3*(1-0.1*(D4-1))*0.04 -> -10000 | E8: =$C$5*(1-0.1*(E4-1))*0.04 -> -9000 | F8: =$C$5*(1-0.1*(F4-1))*0.04 -> -8000 | G8: =$C$5*(1-0.1*(G4-1))*0.04 -> -7000 | H8: =$C$5*(1-0.1*(H4-1))*0.04 -> -6000
B9: Impuestos | D9: 0 | E9: 0 | F9: 0 | G9: 0 | H9: 0
B10: Almacenamiento | D10: =-5*365 -> -1825 | E10: =D10 -> -1825 | F10: =E10 -> -1825 | G10: =F10 -> -1825 | H10: =G10 -> -1825
B11: Mantenimiento preventivo | D11: =-5000/250*500 -> -10000 | E11: =D11 -> -10000 | F11: =E11 -> -10000 | G11: =F11 -> -10000 | H11: =G11 -> -10000
B12: Elementos de desgaste | D12: =-15000 -> -15000 | E12: =D12 -> -15000 | F12: =E12 -> -15000 | G12: =F12 -> -15000 | H12: =G12 -> -15000
B13: Herramientas de corte | D13: =-8000 -> -8000 | E13: =D13 -> -8000 | F13: =E13 -> -8000 | G13: =F13 -> -8000 | H13: =G13 -> -8000
B14: Neumáticos | D14: -30000 | E14: =D14 -> -30000 | F14: =E14 -> -30000 | G14: =F14 -> -30000 | H14: =G14 -> -30000
B15: Combustible | D15: =-(4.5*15000/3)*11.5/3.35 -> -77238.806 | E15: =D15 -> -77238.806 | F15: =E15 -> -77238.806 | G15: =F15 -> -77238.806 | H15: =G15 -> -77238.806
B16: Mantenimiento correctivo | D16: =-3600 -> -3600 | E16: =D16 -> -3600 | F16: =E16 -> -3600 | G16: =F16 -> -3600 | H16: =G16 -> -3600
B17: Equipo back up | D17: =-('Tiempo mantenimiento'!D22)*720 -> -17045.741 | E17: =D17 -> -17045.741 | F17: =E17 -> -17045.741 | G17: =F17 -> -17045.741 | H17: =G17 -> -17045.741
B18: Perdida de producción | D18: =-'Tiempo mantenimiento'!D22*'Tiempo mantenimiento'!B14*'Caso Excavadora'!G7*(150-125) -> -4864.6521 | E18: =D18 -> -4864.6521 | F18: =E18 -> -4864.6521 | G18: =F18 -> -4864.6521 | H18: =G18 -> -4864.6521
B19: Flujo de caja | C19: =SUM(C5:C18) -> -250000 | D19: =SUM(D8:D18) -> -177574.2 | E19: =SUM(E8:E18) -> -176574.2 | F19: =SUM(F8:F18)+F7 -> -175574.2 | G19: =SUM(G8:G18)+G7 -> -174574.2 | H19: =SUM(H8:H18)+H7 -> -23574.199
B20: VALOR NETO ACTUAL | C20: =C19+NPV(C2,D19:H19) -> -755562.4
B23: HORAS ANUALES (150 m3/h) | D23: =3000-'Tiempo mantenimiento'!D22*'Tiempo mantenimiento'!B14 -> 2805.4139 | E23: =D23 -> 2805.4139 | F23: =E23 -> 2805.4139 | G23: =F23 -> 2805.4139 | H23: =G23 -> 2805.4139
B24: HORAS ANUALES (125 m3/h) | D24: ='Tiempo mantenimiento'!D22*'Tiempo mantenimiento'!B14 -> 194.58608 | E24: =D24 -> 194.58608 | F24: =E24 -> 194.58608 | G24: =F24 -> 194.58608 | H24: =G24 -> 194.58608
B25: PRODUCCIÓN (m3) | D25: =D23*150+D24*125 -> 445135.35 | E25: =D25 -> 445135.35 | F25: =E25 -> 445135.35 | G25: =F25 -> 445135.35 | H25: =G25 -> 445135.35
B26: INGRESOS (USD) | D26: =D25*'Caso Excavadora'!G7 -> 445135.35 | E26: =D26 -> 445135.35 | F26: =E26 -> 445135.35 | G26: =F26 -> 445135.35 | H26: =G26 -> 445135.35
